freesimplejson/__main__.py
freesimplejson/main.py
pysimplejson-0.1.3.dist-info/METADATA
pysimplejson-0.1.3.dist-info/WHEEL
pysimplejson-0.1.3.dist-info/entry_points.txt
pysimplejson-0.1.3.dist-info/top_level.txt
pysimplejson-0.1.3.dist-info/RECORD
