Metadata-Version: 2.4
Name: pysimplejson
Version: 0.1.3
Summary: A user-friendly tool to view, analyze, and interact with JSON and JSONL data.
Requires-Python: >=3.12
Requires-Dist: freesimplegui>=5.2.0.post1
Requires-Dist: jsonpath-ng>=1.7.0
